demo_app/migrations/__init__.py
demo_app/migrations/__pycache__/__init__.cpython-36.pyc
demo_app/migrations/__pycache__/__init__.cpython-38.pyc
demo_site/settings/__init__.py
demo_site/settings/base.py
demo_site/settings/development.py
demo_site/settings/local.py
demo_site/settings/production.py
demo_site/settings/__pycache__/__init__.cpython-36.pyc
demo_site/settings/__pycache__/__init__.cpython-38.pyc
demo_site/settings/__pycache__/base.cpython-36.pyc
demo_site/settings/__pycache__/base.cpython-38.pyc
demo_site/settings/__pycache__/development.cpython-36.pyc
demo_site/settings/__pycache__/development.cpython-38.pyc
demo_site/settings/__pycache__/local.cpython-36.pyc
demo_site/settings/__pycache__/local.cpython-38.pyc
materialize_nav/__init__.py
materialize_nav/__meta__.py
materialize_nav/colors.py
materialize_nav/context_processors.py
materialize_nav/forms.py
materialize_nav/models.py
materialize_nav/settings.py
materialize_nav/utils.py
materialize_nav/__pycache__/__init__.cpython-36.pyc
materialize_nav/__pycache__/__init__.cpython-38.pyc
materialize_nav/__pycache__/__meta__.cpython-36.pyc
materialize_nav/__pycache__/__meta__.cpython-38.pyc
materialize_nav/__pycache__/colors.cpython-36.pyc
materialize_nav/__pycache__/colors.cpython-38.pyc
materialize_nav/__pycache__/context_processors.cpython-36.pyc
materialize_nav/__pycache__/context_processors.cpython-38.pyc
materialize_nav/__pycache__/forms.cpython-36.pyc
materialize_nav/__pycache__/forms.cpython-38.pyc
materialize_nav/__pycache__/models.cpython-36.pyc
materialize_nav/__pycache__/models.cpython-38.pyc
materialize_nav/__pycache__/settings.cpython-36.pyc
materialize_nav/__pycache__/settings.cpython-38.pyc
materialize_nav/__pycache__/utils.cpython-36.pyc
materialize_nav/__pycache__/utils.cpython-38.pyc
materialize_nav/static/accounts/default_background.png
materialize_nav/static/accounts/default_user.png
materialize_nav/static/materialize_nav/materialize_nav.css
django_materialize_nav-1.2.0.dist-info/LICENSE
django_materialize_nav-1.2.0.dist-info/METADATA
django_materialize_nav-1.2.0.dist-info/WHEEL
django_materialize_nav-1.2.0.dist-info/top_level.txt
django_materialize_nav-1.2.0.dist-info/RECORD
