Metadata-Version: 2.1
Name: django-materialize-nav
Version: 1.2.0
Summary: Django materialize css support.
Home-page: https://github.com/justengel-django/django_materialize_nav
Author: Justin Engel
Author-email: jtengel08@gmail.com
License: Proprietary
Download-URL: https://github.com/justengel-django/django_materialize_nav/archive/v1.2.0.tar.gz
Keywords: Django Materialize CSS
Platform: any
Classifier: Programming Language :: Python
Classifier: Programming Language :: Python :: 3
Classifier: Operating System :: OS Independent
Classifier: Framework :: Django :: 2.0
Classifier: License :: OSI Approved :: MIT License
